bubububusinka/__init__.py
bubububusinka/__main__.py
bubububusinka/main.py
bubububusinka-0.0.6.dist-info/METADATA
bubububusinka-0.0.6.dist-info/WHEEL
bubububusinka-0.0.6.dist-info/licenses/LICENSE
bubububusinka-0.0.6.dist-info/RECORD
