Metadata-Version: 2.4
Name: bubububusinka
Version: 0.0.6
Summary: meow
Author-email: mirkuriit <Tot-kto-idet@yandex.ru>
License-File: LICENSE
Classifier: License :: OSI Approved :: MIT License
Classifier: Operating System :: OS Independent
Classifier: Programming Language :: Python :: 3
Requires-Python: >=3.10.0
Requires-Dist: openai
